mate_selection-0.1.1.dist-info/METADATA
mate_selection-0.1.1.dist-info/WHEEL
mate_selection-0.1.1.dist-info/licenses/LICENSE.txt
mate_selection.libs/libgcc_s-b5472b99.so.1
mate_selection/__init__.py
mate_selection/mate_selection.cpython-313t-i386-linux-musl.so
mate_selection-0.1.1.dist-info/RECORD
