Metadata-Version: 2.3
Name: mate_selection
Version: 0.1.1
Classifier: Development Status :: 5 - Production/Stable
Classifier: License :: OSI Approved :: MIT No Attribution License (MIT-0)
Classifier: Natural Language :: English
Classifier: Intended Audience :: Science/Research
Classifier: Topic :: Scientific/Engineering
Classifier: Programming Language :: Python
License-File: LICENSE.txt
Summary: A collection of mate selection methods for evolutionary algorithms
Keywords: algorithms,random,sampling
Author: David McDougall <dam1784@rit.edu>
Author-email: David McDougall <dam1784@rit.edu>
License: MIT-0
Requires-Python: >=3.8
Project-URL: repository, https://github.com/ctrl-z-9000-times/mate_selection.git
